bandit_tools/__init__.py
bandit_tools/baseline_tools.py
bandit_tools/custom_report.py
bandit_tools-0.0.1.dist-info/LICENSE
bandit_tools-0.0.1.dist-info/METADATA
bandit_tools-0.0.1.dist-info/WHEEL
bandit_tools-0.0.1.dist-info/entry_points.txt
bandit_tools-0.0.1.dist-info/top_level.txt
bandit_tools-0.0.1.dist-info/RECORD
