Metadata-Version: 2.1
Name: bandit-tools
Version: 0.0.1
Summary: Basic Tools for improve Bandit
Home-page: https://github.com/ehooo/bandit_tools/
Author: Victor Torre
Author-email: web.ehooo@gmail.com
License: Apache 2
Keywords: testing,security,bandit
Platform: UNKNOWN
Classifier: License :: OSI Approved :: Apache Software License
Classifier: Operating System :: OS Independent
Classifier: Programming Language :: Python :: 2.7
Classifier: Programming Language :: Python :: 3.5
Classifier: Programming Language :: Python :: 3.6
Classifier: Programming Language :: Python :: 3.7
Classifier: Topic :: Security
Requires-Dist: jinja2
Requires-Dist: bandit
